nebuly/__init__.py
nebuly/ab_testing/__init__.py
nebuly/ab_testing/main.py
nebuly/ab_testing/types.py
nebuly/api_key.py
nebuly/config.py
nebuly/consumers.py
nebuly/contextmanager.py
nebuly/entities.py
nebuly/event_parsers.py
nebuly/events.py
nebuly/exceptions.py
nebuly/init.py
nebuly/monkey_patching.py
nebuly/observers.py
nebuly/providers/__init__.py
nebuly/providers/anthropic.py
nebuly/providers/aws_bedrock.py
nebuly/providers/base.py
nebuly/providers/cohere.py
nebuly/providers/common.py
nebuly/providers/google.py
nebuly/providers/huggingface.py
nebuly/providers/huggingface_hub.py
nebuly/providers/langchain.py
nebuly/providers/llama_index.py
nebuly/providers/openai.py
nebuly/providers/openai_legacy.py
nebuly/providers/utils.py
nebuly/providers/vertexai.py
nebuly/requests.py
nebuly/tracking/__init__.py
nebuly/tracking/actions.py
nebuly/tracking/types.py
nebuly/utils.py
nebuly-0.3.38.dist-info/METADATA
nebuly-0.3.38.dist-info/WHEEL
nebuly-0.3.38.dist-info/RECORD
