Metadata-Version: 2.1
Name: nebuly
Version: 0.3.38
Summary: The SDK for instrumenting applications for tracking AI costs.
Author: Nebuly
Requires-Python: >=3.9,<4.0
Classifier: Programming Language :: Python :: 3
Classifier: Programming Language :: Python :: 3.9
Classifier: Programming Language :: Python :: 3.10
Classifier: Programming Language :: Python :: 3.11
Classifier: Programming Language :: Python :: 3.12
Requires-Dist: packaging (>=23.2,<24.0)
